baltech_sdk/__init__.py
baltech_sdk/baltech_api/__init__.py
baltech_sdk/baltech_api/baltech_script.py
baltech_sdk/baltech_api/commands.py
baltech_sdk/baltech_api/common.py
baltech_sdk/baltech_api/configuration.py
baltech_sdk/baltech_api/template.py
baltech_sdk/baltech_api/typedefs.py
baltech_sdk/brp_lib/__init__.py
baltech_sdk/brp_lib/brp_lib.win32.dll
baltech_sdk/brp_lib/brp_lib.win64.dll
baltech_sdk/brp_lib/dll_wrapper.py
baltech_sdk/brp_lib/protocols.py
baltech_sdk/errors.py
baltech_sdk/py.typed
baltech_sdk-3.19.4.dist-info/METADATA
baltech_sdk-3.19.4.dist-info/WHEEL
baltech_sdk-3.19.4.dist-info/RECORD
