Metadata-Version: 2.1
Name: baltech-sdk
Version: 3.19.4
Summary: SDK to communicate with Baltech RFID readers.
License: MIT
Author: Baltech AG
Author-email: info@baltech.de
Requires-Python: >=3.9,<4.0
Classifier: License :: OSI Approved :: MIT License
Classifier: Programming Language :: Python :: 3
Classifier: Programming Language :: Python :: 3.9
Classifier: Programming Language :: Python :: 3.10
Classifier: Programming Language :: Python :: 3.11
Classifier: Programming Language :: Python :: 3.12
Requires-Dist: typing-extensions
